{"entryPoints":["src/app/docs/[category]/[slug]/page.tsx","src/app/docs/[category]/page.tsx","src/app/docs/page.tsx","src/app/page.tsx","src/app/studio/[[...index]]/page.tsx","src/sanity/schemaTypes/index.ts"],"modules":[{"module":"next.config.ts","files":["next.config.ts"],"imports":["next"],"exports":["export default nextConfig;"]},{"module":"sanity.cli.ts","files":["sanity.cli.ts"],"imports":["sanity/cli"],"exports":["export default defineCliConfig({"]},{"module":"sanity.config.ts","files":["sanity.config.ts"],"imports":["sanity","sanity/structure","@sanity/code-input","./src/sanity/schemaTypes"],"exports":["export default defineConfig({"]},{"module":"scripts","files":["scripts/seed_content.ts"],"imports":["next-sanity"],"exports":[]},{"module":"src","files":["src/app/docs/[category]/[slug]/page.tsx","src/app/docs/[category]/page.tsx","src/app/docs/layout.tsx","src/app/docs/page.tsx","src/app/layout.tsx","src/app/page.tsx","src/app/studio/[[...index]]/page.tsx","src/components/PortableTextContent.tsx","src/components/ReadingProgress.tsx","src/components/SearchPalette.tsx","src/components/Sidebar.tsx","src/components/SidebarLink.tsx","src/components/SidebarShell.tsx","src/components/TableOfContents.tsx","src/sanity/lib/client.ts","src/sanity/schemaTypes/categoryType.ts","src/sanity/schemaTypes/index.ts","src/sanity/schemaTypes/postType.ts"],"imports":["@/sanity/lib/client","@/components/PortableTextContent","@/components/ReadingProgress","@/components/TableOfContents","next/link","next/navigation","@/sanity/lib/client","next/link","next/navigation","@/components/Sidebar","next/link","@/sanity/lib/client","next","next/font/google","./globals.css","@/sanity/lib/client","next/link","next-sanity/studio","../../../../sanity.config","@portabletext/react","shiki","react","react","next/navigation","next-sanity","next/link","@/sanity/lib/client","./SidebarLink","./SidebarShell","next/link","next/navigation","react","./SearchPalette","react","next-sanity","sanity","sanity","./postType","./categoryType","sanity"],"exports":["export default async function ArticlePage({ params }: ArticlePageProps)","export default async function CategoryPage({ params }: CategoryPageProps)","export default function DocsLayout({","export default async function DocsLanding()","export const metadata: Metadata =","export default function RootLayout({","export default async function HomePage()","export default function StudioPage()","export function PortableTextContent({ value }:","export function ReadingProgress()","export function SearchPalette({ isOpen, onClose }: SearchPaletteProps)","export async function Sidebar()","export function SidebarLink({ href, children }: SidebarLinkProps)","export function SidebarShell({ children }:","export function TableOfContents({ body }: TableOfContentsProps)","export const client = createClient({","export const categoryType = defineType({","export const schema:","export const postType = defineType({"]}],"graph":[{"dependsOn":[],"externalDeps":["next"]},{"dependsOn":[],"externalDeps":["sanity"]},{"dependsOn":[],"externalDeps":["sanity","@sanity"]},{"dependsOn":[],"externalDeps":["next-sanity"]},{"dependsOn":[],"externalDeps":["@","next","next-sanity","@portabletext","shiki","react","sanity"]}],"latestFiles":["next.config.ts","sanity.cli.ts","sanity.config.ts","scripts/seed_content.ts","src/app/docs/[category]/[slug]/page.tsx","src/app/docs/[category]/page.tsx","src/app/docs/layout.tsx","src/app/docs/page.tsx","src/app/layout.tsx","src/app/page.tsx","src/app/studio/[[...index]]/page.tsx","src/components/PortableTextContent.tsx","src/components/ReadingProgress.tsx","src/components/SearchPalette.tsx","src/components/Sidebar.tsx","src/components/SidebarLink.tsx","src/components/SidebarShell.tsx","src/components/TableOfContents.tsx","src/sanity/lib/client.ts","src/sanity/schemaTypes/categoryType.ts","src/sanity/schemaTypes/index.ts","src/sanity/schemaTypes/postType.ts"]}